__init__.py
neu.py
website_url_finder.py
google_search/__init__.py
google_search/google_search.py
link_extractor/__init__.py
link_extractor/link_extractor.py
onlinetorch_website_url_finder-0.1.2.dist-info/DESCRIPTION.rst
onlinetorch_website_url_finder-0.1.2.dist-info/METADATA
onlinetorch_website_url_finder-0.1.2.dist-info/RECORD
onlinetorch_website_url_finder-0.1.2.dist-info/WHEEL
onlinetorch_website_url_finder-0.1.2.dist-info/metadata.json
onlinetorch_website_url_finder-0.1.2.dist-info/top_level.txt
