Metadata-Version: 2.0
Name: onlinetorch-website-url-finder
Version: 0.1.2
Summary: Python Onlinetorch Project Finding website url from name
Home-page: UNKNOWN
Author: Benedikt Schmeitz
Author-email: UNKNOWN
License: UNKNOWN
Platform: UNKNOWN
